donapram/__init__.py
donapram/donapram.pyd
donapram-1.0.0.dist-info/METADATA
donapram-1.0.0.dist-info/WHEEL
donapram-1.0.0.dist-info/top_level.txt
donapram-1.0.0.dist-info/RECORD
