Metadata-Version: 2.4
Name: donapram
Version: 1.0.0
Summary: Module Python basé sur une DLL externe
Author-email: Leonel Taffoup <leonelbrice@gmail.com>
License: MIT
Requires-Python: >=3.14
